{
  "dependencies": {
    "chai": "^3.5.0",
    "coffeelint": "1.x.x",
    "gulp": "^3.9.1",
    "gulp-cached": "1.x.x",
    "gulp-coffee": "2.x.x",
    "gulp-coffeelint": "0.x.x",
    "gulp-debounced-watch": "1.x.x",
    "gulp-filter": "4.x.x",
    "gulp-help": "1.x.x",
    "gulp-load-plugins": "^1.4.0",
    "gulp-size": "^2.1.0",
    "gulp-using": "^0.1.1",
    "sinon": "^1.17.5",
    "sinon-chai": "^2.8.0",
    "commitizen": "^2.9.5",
    "cz-conventional-changelog": "^1.2.0",
    "semantic-release": "^6.3.2",
    "node-yaml": "^3.0.3"
  }
}
